shenv/__init__.py
shenv/shenv.py
shenv-0.0.1.dist-info/LICENSE
shenv-0.0.1.dist-info/METADATA
shenv-0.0.1.dist-info/WHEEL
shenv-0.0.1.dist-info/entry_points.txt
shenv-0.0.1.dist-info/top_level.txt
shenv-0.0.1.dist-info/RECORD
