Metadata-Version: 2.2
Name: shenv
Version: 0.0.1
Summary: Easily manage per-project environment variables.
Maintainer-email: Alex Laird <contact@alexlaird.com>
License: MIT License
Project-URL: Changelog, https://github.com/alexdlaird/shenv/blob/main/CHANGELOG.md
Project-URL: Sponsor, https://github.com/sponsors/alexdlaird
Project-URL: Source Code, https://github.com/alexdlaird/shenv
Classifier: Development Status :: 2 - Pre-Alpha
Classifier: Environment :: Console
Classifier: Environment :: Web Environment
Classifier: Intended Audience :: Developers
Classifier: Intended Audience :: System Administrators
Classifier: License :: OSI Approved :: MIT License
Classifier: Operating System :: OS Independent
Classifier: Programming Language :: Python :: 3
Classifier: Programming Language :: Python :: 3.8
Classifier: Programming Language :: Python :: 3.9
Classifier: Programming Language :: Python :: 3.10
Classifier: Programming Language :: Python :: 3.11
Classifier: Programming Language :: Python :: 3.12
Classifier: Topic :: Software Development :: Testing
Classifier: Topic :: Software Development :: Build Tools
Classifier: Topic :: Software Development :: Libraries :: Python Modules
Requires-Python: >=3.8
License-File: LICENSE
Requires-Dist: PyYAML>=5.1
Provides-Extra: dev
Requires-Dist: pytest; extra == "dev"
Requires-Dist: coverage[toml]; extra == "dev"
Requires-Dist: flake8; extra == "dev"
Requires-Dist: flake8-pyproject; extra == "dev"
Requires-Dist: pep8-naming; extra == "dev"
